rubxy/__init__.py
rubxy/_config.py
rubxy/client.py
rubxy/dispatcher.py
rubxy/filters.py
rubxy/sync.py
rubxy/enums/__init__.py
rubxy/enums/auto_name.py
rubxy/enums/button_calendar_type.py
rubxy/enums/button_location_type.py
rubxy/enums/button_selection_get.py
rubxy/enums/button_selection_search.py
rubxy/enums/button_selection_type.py
rubxy/enums/button_textbox_type_keypad.py
rubxy/enums/button_textbox_type_line.py
rubxy/enums/button_type.py
rubxy/enums/chat_keypad_type.py
rubxy/enums/chat_type.py
rubxy/enums/event_type.py
rubxy/enums/file_type.py
rubxy/enums/forwarded_from.py
rubxy/enums/live_location_status.py
rubxy/enums/parse_mode.py
rubxy/enums/payment_status.py
rubxy/enums/poll_status.py
rubxy/enums/sender_type.py
rubxy/enums/update_endpoint_type.py
rubxy/enums/update_type.py
rubxy/errors/__init__.py
rubxy/errors/exceptions/__init__.py
rubxy/errors/exceptions/api_error.py
rubxy/errors/exceptions/invalid_access.py
rubxy/errors/exceptions/invalid_input.py
rubxy/errors/exceptions/invalid_method.py
rubxy/errors/exceptions/too_requests.py
rubxy/handlers/__init__.py
rubxy/handlers/handler.py
rubxy/handlers/inline_message_handler.py
rubxy/handlers/message_handler.py
rubxy/handlers/start_handler.py
rubxy/handlers/stop_handler.py
rubxy/methods/__init__.py
rubxy/methods/advanced/__init__.py
rubxy/methods/advanced/invoke.py
rubxy/methods/chats/__init__.py
rubxy/methods/chats/ban_chat_member.py
rubxy/methods/chats/get_chat.py
rubxy/methods/chats/unban_chat_member.py
rubxy/methods/decorators/__init__.py
rubxy/methods/decorators/on_inline_message.py
rubxy/methods/decorators/on_message.py
rubxy/methods/decorators/on_start.py
rubxy/methods/decorators/on_stop.py
rubxy/methods/messages/__init__.py
rubxy/methods/messages/delete_message.py
rubxy/methods/messages/edit_chat_keypad.py
rubxy/methods/messages/edit_message_keypad.py
rubxy/methods/messages/edit_message_text.py
rubxy/methods/messages/forward_message.py
rubxy/methods/messages/get_file.py
rubxy-1.1.1.dist-info/licenses/LICENSE
rubxy-1.1.1.dist-info/METADATA
rubxy-1.1.1.dist-info/WHEEL
rubxy-1.1.1.dist-info/top_level.txt
rubxy-1.1.1.dist-info/RECORD
